graph/__init__.py
graph/builder.py
adimis_graph_builder-0.0.2.dist-info/METADATA
adimis_graph_builder-0.0.2.dist-info/WHEEL
adimis_graph_builder-0.0.2.dist-info/top_level.txt
adimis_graph_builder-0.0.2.dist-info/RECORD
