Metadata-Version: 2.1
Name: adimis_graph_builder
Version: 0.0.2
Summary: Core utilities for the Adimis toolbox.
Home-page: https://github.com/adimis-ai/adimis-toolbox-core
Author: Aditya Mishra
Author-email: aditya.mishra@adimis.in
Classifier: Programming Language :: Python :: 3
Classifier: License :: OSI Approved :: MIT License
Classifier: Operating System :: OS Independent
Requires-Python: >=3.7
Requires-Dist: aiohappyeyeballs==2.4.3
Requires-Dist: aiohttp==3.11.7
Requires-Dist: aiosignal==1.3.1
Requires-Dist: amqp==5.3.1
Requires-Dist: annotated-types==0.7.0
Requires-Dist: anyio==4.6.2.post1
Requires-Dist: asgiref==3.8.1
Requires-Dist: attrs==24.2.0
Requires-Dist: autobahn==24.4.2
Requires-Dist: Automat==24.8.1
Requires-Dist: beautifulsoup4==4.12.3
Requires-Dist: billiard==4.2.1
Requires-Dist: cachetools==5.5.0
Requires-Dist: celery==5.4.0
Requires-Dist: certifi==2024.8.30
Requires-Dist: cffi==1.17.1
Requires-Dist: charset-normalizer==3.4.0
Requires-Dist: click==8.1.7
Requires-Dist: click-didyoumean==0.3.1
Requires-Dist: click-plugins==1.1.1
Requires-Dist: click-repl==0.3.0
Requires-Dist: constantly==23.10.4
Requires-Dist: cryptography==44.0.0
Requires-Dist: daphne==4.1.2
Requires-Dist: dataclasses-json==0.6.7
Requires-Dist: Deprecated==1.2.15
Requires-Dist: distro==1.9.0
Requires-Dist: docutils==0.21.2
Requires-Dist: duckduckgo_search==6.3.7
Requires-Dist: frozenlist==1.5.0
Requires-Dist: google-ai-generativelanguage==0.6.10
Requires-Dist: google-api-core==2.23.0
Requires-Dist: google-api-python-client==2.154.0
Requires-Dist: google-auth==2.36.0
Requires-Dist: google-auth-httplib2==0.2.0
Requires-Dist: google-generativeai==0.8.3
Requires-Dist: googleapis-common-protos==1.66.0
Requires-Dist: greenlet==3.1.1
Requires-Dist: grpcio==1.68.0
Requires-Dist: grpcio-status==1.68.0
Requires-Dist: gunicorn==23.0.0
Requires-Dist: h11==0.14.0
Requires-Dist: httpcore==1.0.7
Requires-Dist: httplib2==0.22.0
Requires-Dist: httpx==0.27.2
Requires-Dist: httpx-sse==0.4.0
Requires-Dist: hyperlink==21.0.0
Requires-Dist: idna==3.10
Requires-Dist: incremental==24.7.2
Requires-Dist: inflection==0.5.1
Requires-Dist: jaraco.classes==3.4.0
Requires-Dist: jaraco.context==6.0.1
Requires-Dist: jaraco.functools==4.1.0
Requires-Dist: jeepney==0.8.0
Requires-Dist: jiter==0.7.1
Requires-Dist: jsonpatch==1.33
Requires-Dist: jsonpointer==3.0.0
Requires-Dist: jsonschema==4.23.0
Requires-Dist: jsonschema-specifications==2024.10.1
Requires-Dist: keyring==25.5.0
Requires-Dist: kombu==5.4.2
Requires-Dist: langchain==0.3.8
Requires-Dist: langchain-community==0.3.8
Requires-Dist: langchain-core==0.3.21
Requires-Dist: langchain-google-genai==2.0.5
Requires-Dist: langchain-openai==0.2.9
Requires-Dist: langchain-postgres==0.0.12
Requires-Dist: langchain-text-splitters==0.3.2
Requires-Dist: langgraph==0.2.53
Requires-Dist: langgraph-checkpoint==2.0.5
Requires-Dist: langgraph-checkpoint-postgres==2.0.4
Requires-Dist: langgraph-sdk==0.1.36
Requires-Dist: langsmith==0.1.145
Requires-Dist: markdown-it-py==3.0.0
Requires-Dist: marshmallow==3.23.1
Requires-Dist: mdurl==0.1.2
Requires-Dist: more-itertools==10.5.0
Requires-Dist: msgpack==1.1.0
Requires-Dist: multidict==6.1.0
Requires-Dist: mypy-extensions==1.0.0
Requires-Dist: nh3==0.2.20
Requires-Dist: numpy==1.26.4
Requires-Dist: openai==1.55.0
Requires-Dist: orjson==3.10.12
Requires-Dist: packaging==24.2
Requires-Dist: pgvector==0.2.5
Requires-Dist: pillow==11.0.0
Requires-Dist: pkginfo==1.12.0
Requires-Dist: playwright==1.49.0
Requires-Dist: primp==0.8.1
Requires-Dist: prompt_toolkit==3.0.48
Requires-Dist: propcache==0.2.0
Requires-Dist: proto-plus==1.25.0
Requires-Dist: protobuf==5.28.3
Requires-Dist: psycopg==3.2.3
Requires-Dist: psycopg-pool==3.2.4
Requires-Dist: psycopg2==2.9.10
Requires-Dist: pyasn1==0.6.1
Requires-Dist: pyasn1_modules==0.4.1
Requires-Dist: pycparser==2.22
Requires-Dist: pydantic==2.10.1
Requires-Dist: pydantic-settings==2.6.1
Requires-Dist: pydantic_core==2.27.1
Requires-Dist: pyee==12.0.0
Requires-Dist: PyGithub==2.5.0
Requires-Dist: Pygments==2.18.0
Requires-Dist: PyJWT==2.10.1
Requires-Dist: PyNaCl==1.5.0
Requires-Dist: pyOpenSSL==24.3.0
Requires-Dist: pyparsing==3.2.0
Requires-Dist: python-dateutil==2.9.0.post0
Requires-Dist: python-decouple==3.8
Requires-Dist: python-dotenv==1.0.1
Requires-Dist: python-slugify==8.0.4
Requires-Dist: PyYAML==6.0.2
Requires-Dist: readme_renderer==44.0
Requires-Dist: referencing==0.35.1
Requires-Dist: regex==2024.11.6
Requires-Dist: requests==2.32.3
Requires-Dist: requests-toolbelt==1.0.0
Requires-Dist: rfc3986==2.0.0
Requires-Dist: rich==13.9.4
Requires-Dist: rpds-py==0.21.0
Requires-Dist: rsa==4.9
Requires-Dist: SecretStorage==3.3.3
Requires-Dist: service-identity==24.2.0
Requires-Dist: setuptools==75.6.0
Requires-Dist: six==1.16.0
Requires-Dist: sniffio==1.3.1
Requires-Dist: soupsieve==2.6
Requires-Dist: SQLAlchemy==2.0.35
Requires-Dist: sqlparse==0.5.2
Requires-Dist: tenacity==9.0.0
Requires-Dist: text-unidecode==1.3
Requires-Dist: tiktoken==0.8.0
Requires-Dist: tqdm==4.67.1
Requires-Dist: twine==6.0.1
Requires-Dist: Twisted==24.11.0
Requires-Dist: txaio==23.1.1
Requires-Dist: typing-inspect==0.9.0
Requires-Dist: typing_extensions==4.12.2
Requires-Dist: tzdata==2024.2
Requires-Dist: uritemplate==4.1.1
Requires-Dist: urllib3==2.2.3
Requires-Dist: uvicorn==0.32.1
Requires-Dist: vine==5.1.0
Requires-Dist: wcwidth==0.2.13
Requires-Dist: wrapt==1.17.0
Requires-Dist: yarl==1.18.0
Requires-Dist: zope.interface==7.2
